{
  "relationships": [
    {
      "relationshipId": 1,
      "relationshipName": "inscription",
      "otherEntityName": "inscription",
      "relationshipType": "many-to-one",
      "otherEntityField": "id"
    }
  ],
  "fields": [
    {
      "fieldId": 1,
      "fieldName": "moment",
      "fieldType": "MomentEnum",
      "fieldValues": "SATURDAY_MORNING,SATURDAY_AFTERNOON,SUNDAY_MORNING"
    }
  ],
  "changelogDate": "20160327172434",
  "dto": "no",
  "pagination": "infinite-scroll",
  "service": "no"
}
